scripts/__init__.py
scripts/autocalculation.py
scripts/backgroup.py
scripts/calnohup.py
scripts/config.py
scripts/dataframe.py
scripts/files.py
scripts/gmdkit.py
scripts/molecule.py
scripts/plotting.py
scripts/plotting_v1.py
scripts/running_calnohup.py
hgmd-2.0.1.dist-info/METADATA
hgmd-2.0.1.dist-info/WHEEL
hgmd-2.0.1.dist-info/top_level.txt
hgmd-2.0.1.dist-info/RECORD
