Metadata-Version: 2.1
Name: hgmd
Version: 2.0.1
Summary: Automatic calculation script for VASP calculation
Home-page: UNKNOWN
Author: Jong Goo Park
Author-email: jgp505@gmail.com
License: UNKNOWN
Platform: UNKNOWN
Requires-Python: >=3
Requires-Dist: numpy (>=1.9)
Requires-Dist: pymatgen (>=2019.3.13)
Requires-Dist: matplotlib (>=1.1)
